{
  "status": "live",
  "inception_date": "2026-01-02",
  "as_of_date": "2026-07-22",
  "days_live": 138,
  "nav_latest": 106.82369504393881,
  "period_return": 0.06823695043938804,
  "max_drawdown": -0.141274430660826,
  "current_drawdown": -0.009451749351422345,
  "cagr": 0.11551402021250623,
  "annualized_vol": 0.21982977562329126,
  "sharpe": 0.6107992022643772,
  "sortino": 0.5069691241097438,
  "calmar": 0.8239599194719998,
  "annualization_note": null,
  "strategy_name": "N500 Momentum",
  "benchmark_status": "ok",
  "current_cash": 0.0,
  "notional_capital": 10000000.0,
  "run_timestamp": "2026-07-22T05:53:28Z",
  "latest_rebalance_signal_date": "2026-06-30",
  "latest_rebalance_exec_date": "2026-07-01"
}