{
  "status": "live",
  "inception_date": "2026-01-02",
  "as_of_date": "2026-07-15",
  "days_live": 133,
  "nav_latest": 97.1854998967246,
  "period_return": -0.02814500103275408,
  "max_drawdown": -0.14577829572889545,
  "current_drawdown": -0.0625000686705407,
  "cagr": -0.06174178827482957,
  "annualized_vol": 0.20664805966517472,
  "sharpe": -0.2074785442600042,
  "sortino": -0.16796171958146042,
  "calmar": -0.4266387747708836,
  "annualization_note": null,
  "strategy_name": "NLargeMid250 Momentum",
  "benchmark_status": "unavailable_v1",
  "current_cash": 0.0,
  "notional_capital": 10000000.0,
  "run_timestamp": "2026-07-15T06:16:59Z",
  "latest_rebalance_signal_date": "2026-06-30",
  "latest_rebalance_exec_date": "2026-07-01"
}